[
  {
    "category": "bar",
    "products": [
      {
        "name": "caffè",
        "price": 1.30
      },
      {
        "name": "birra media",
        "price": 5.00
      },
      {
        "name": "birra",
        "price": 2.50
      },
     
      {
        "name": "aperitivi",
        "price": 3
      },
      {
        "name": "snack",
        "price": 2.00
      },
      {
        "name": "panini",
        "price": 4.50
      },
      {
        "name": "specialità",
        "price": 3.50
      },
      {
        "name": "long drink",
        "price": 5.50
      },
      {
        "name": "cappuccino",
        "price": 2.00
      },
      {
        "name": "the e tisane",
        "price": 3.00
      },
      {
        "name": "liquori/grappe",
        "price": 3.50
      },
      {
        "name": "brioches",
        "price": 1.50
      },
      {
        "name": "dolci",
        "price": 3.50
      },
      {
        "name": "vino",
        "price": 3.50
      },
      {
        "name": "bibite",
        "price": 3.00
      },{
        "name": "acqua minerale ½l",
        "price": 1.50
      },{
        "name": "acqua minerale 1l",
        "price": 2.50
      },{
        "name": "spritz",
        "price": 4
      }
    ]
  },
  {
    "category": "ristorante",
    "products": [
      {
        "name": "coperto",
        "price": 2
      },
      {
        "name": "buffet",
        "price": 14
      },
      {
        "name": "buffet baby",
        "price": 8
      },
      {
        "name": "birra",
        "price": 3
      },
      {
        "name": "birra media",
        "price": 5
      },
      {
        "name": "birra grande",
        "price": 5.5
      },
      {
        "name": "bevande",
        "price": 3
      },
      {
        "name": "calice vino",
        "price": 4
      },
      {
        "name": "acqua",
        "price": 2.50
      },
      {
        "name": "dessert",
        "price": 5
      },
      {
        "name": "primo",
        "price": 12
      },
      {
        "name": "secondo",
        "price": 20
      },
      {
        "name": "insalatona",
        "price": 10
      },
      {
        "name": "piatto unico",
        "price": 22
      },
      {
        "name": "contorno",
        "price": 7.50
      },
      {
        "name": "menu",
        "price": 25
      }
    ]
  },
  {
    "category": "vini",
    "products": [
      {
        "name": "St. Magdalener - Rottensteiner",
        "price": 21
      },
      {
        "name": "St. Magdalener select - Rottensteiner",
        "price": 37
      },
      {
        "name": "Kalterersee Auslese - Rottensteiner",
        "price": 19
      },
      {
        "name": "Marzemino Mozart - Concilio",
        "price": 18
      },
      {
        "name": "Marzemino et. bianca - Cantina d'Isera",
        "price": 18
      },
      {
        "name": "Marzemino et. verde - Cantina d'Isera ",
        "price": 24
      },
      {
        "name": "Marzemino Sup. - Maso Salengo",
        "price": 26
      },
      {
        "name": "Teroldego LeAlbere - Zeni",
        "price": 26
      },
      {
        "name": "Teroldego 75cl Firmian - Mezzocorona",
        "price": 19
      },
      {
        "name": "Teroldego 35cl Firmian - Mezzocorona",
        "price": 10
      },
      {
        "name": "teroldego Riserva - Mezzocorona",
        "price": 25
      },
      {
        "name": "Lagrein Riserva - Rottensteiner",
        "price": 27
      },
      {
        "name": "Lagrein Riserva - Mezzocorona",
        "price": 27
      },
      {
        "name": "Navesel - Simoncelli",
        "price": 27
      },
      {
        "name": "Nomer - Grigoletti",
        "price": 18
      },
      {
        "name": "Merlot Antica Vigna - Grigoletti",
        "price": 32
      },
      {
        "name": "Gonzalier - Grigoletti",
        "price": 38
      },
      {
        "name": "Mori Vecio - Concilio",
        "price": 29
      },
      {
        "name": "Pinot Nero 75cl - Pojer e Sandri",
        "price": 26
      },
      {
        "name": "Pinot Nero 35cl - Pojer e Sandri",
        "price": 18
      },
      {
        "name": "Pinot Nero Monkner - Concilio",
        "price": 21
      },
      {
        "name": "Valdadige Riserva - Viticoltori di Avio",
        "price": 27
      },
      {
        "name": "Valdadige - Viticoltori di Avio",
        "price": 20
      },
      {
        "name": "San Leonardo",
        "price": 92
      },
      {
        "name": "Lagrein Knott - Concilio",
        "price": 20
      },
      {
        "name": "Terre Noce - Mezzocorona",
        "price": 12
      },
      {
        "name": "Barbera - Baracco de Baracho",
        "price": 19
      },
      {
        "name": "Amarone - Brigaldara",
        "price": 61
      },
      {
        "name": "Bardolino - Giovanna Tantini",
        "price": 18
      },
      {
        "name": "Refosco - Tenuta Pinni",
        "price": 18
      },
      {
        "name": "Morellino di Scansano - Provveditore",
        "price": 20
      },
      {
        "name": "Chianti BIO - La Lastra",
        "price": 20
      },
      {
        "name": "Brunello di Montalcino - Palazzo",
        "price": 60
      },
      {
        "name": "Pinot Noir - Saget La Perrièr",
        "price": 23
      },
      {
        "name": "Bordeaux - Chateau Sainte-Marie",
        "price": 28
      },
      {
        "name": "L'Opera - Grigoletti",
        "price": 24
      },
      {
        "name": "Riesling Renano - Pelz",
        "price": 23
      },
      {
        "name": "Sylvaner - Villscheider",
        "price": 26
      },
      {
        "name": "Retiko - Grigoletti",
        "price": 28
      },
      {
        "name": "Muller Palai 75 cl - Pojer e Sandri",
        "price": 26
      },
      {
        "name": "Muller Palai 35 cl - Pojer e Sandri",
        "price": 15
      },
      {
        "name": "Muller Thurgau - Concilio",
        "price": 20
      },
      {
        "name": "Gewurztraminer - Concilio",
        "price": 25
      },
      {
        "name": "Traminer Aromatico - Pojer e Sandri",
        "price": 26
      },
      {
        "name": "Pinot Grigio Ramato - Pravis",
        "price": 20
      },
      {
        "name": "Fil di rose P. Grigio Rose - Mezzocorona",
        "price": 20
      },
      {
        "name": "Pinot Grigio - Concilio",
        "price": 19
      },
      {
        "name": "Pinot Grigio Riserva - Mezzocorona",
        "price": 25
      },
      {
        "name": "Nosiola - Pojer e Sandri",
        "price": 22
      },
      {
        "name": "Terre del Noce - Mezzocorona",
        "price": 12
      },
      {
        "name": "Soave Classico - Le Battistelle",
        "price": 21
      },
      {
        "name": "Friuliano Collio - Simon Komjanc",
        "price": 21
      },
      {
        "name": "Blanc de Morgex de la Salle - Cave Mont Blanc",
        "price": 25
      },
      {
        "name": "Lagrein Rosé - Rottensteiner",
        "price": 22
      },
      {
        "name": "Lagrein Rosato - Castel Firmian",
        "price": 18
      },
      {
        "name": "Vin dei Molini - Pojer e Sandri",
        "price": 20
      },
      {
        "name": "Bardolino Chiaretto - Giovanna Tantini",
        "price": 18
      },
      {
        "name": "Perlè - Ferrari",
        "price": 67
      },
      {
        "name": "Cuvee Brut - Rotari",
        "price": 24
      },
      {
        "name": "Lilium - Concilio",
        "price": 18
      },
      {
        "name": "TrentoDoc 1907 - Cantina d'Isera",
        "price": 30
      },
      {
        "name": "Prosecco - Valdobbiadene",
        "price": 18
      },
      {
        "name": "TrentoDoc 601 - Concilio",
        "price": 28
      },
      {
        "name": "Rosé - Pojer e Sandri",
        "price": 37
      },
      {
        "name": "Prime Rose - Cavit",
        "price": 18
      },
      {
        "name": "Lambrusco - Barbolin",
        "price": 18
      },
      {
        "name": "San Martin - Grigoletti",
        "price": 27
      },
      {
        "name": "Castel Beseno Sup. - Cantina di Trento",
        "price": 27
      },
      {
        "name": "Gewurztraminer Goccia d'oro - Cantina Sociale di Trento",
        "price": 25
      },
      {
        "name": "Chardonnay Heredia - Cantina Sociale di Trento",
        "price": 20
      },
      {
        "name": "Rebo - Cantina Sociale di Trento",
        "price": 21
      },
      {
        "name": "Zell Brut - Cantina Sociale di Trento",
        "price": 37
      }
    ]
  },
  {
    "category": "spa",
    "products": [
      {
        "name": "kit wellness",
        "price": 10
      },
      {
        "name": "maori",
        "price": 65
      },
      {
        "name": "scrub corpo",
        "price": 40
      },
      {
        "name": "sportivo defaticante",
        "price": 65
      },
      {
        "name": "accappatoio",
        "price": 7
      },
      {
        "name": "telo",
        "price": 4
      },
      {
        "name": "ciabatte",
        "price": 2
      },
      {
        "name": "aromatherapy massage",
        "price": 50
      },
      {
        "name": "decontratturante schiena",
        "price": 35
      },
      {
        "name": "personalizzato",
        "price": 60
      },
      {
        "name": "lomi lomi",
        "price": 60
      },
      {
        "name": "linfodrenaggui vooder",
        "price": 70
      },
      {
        "name": "drenante parziale",
        "price": 35
      },
      {
        "name": "drenante totale",
        "price": 55
      },
      {
        "name": "riflessologia plantare",
        "price": 35
      },
      {
        "name": "hot stone",
        "price": 65
      },
      {
        "name": "bimbi",
        "price": 30
      },
      {
        "name": "viso, collo e spalle",
        "price": 30
      },
      {
        "name": "cielo e terra",
        "price": 35
      },
      {
        "name": "scrub corpo",
        "price": 55
      },
      {
        "name": "leggerezza con bendaggi",
        "price": 60
      },
      {
        "name": "alghe body slim",
        "price": 65
      },
      {
        "name": "purezza profonda",
        "price": 55
      },
      {
        "name": "idratazione intensa",
        "price": 50
      },
      {
        "name": "idratazione intensa",
        "price": 50
      },
      {
        "name": "sublime lift",
        "price": 50
      },
      {
        "name": "antiage illuminante",
        "price": 50
      }
    ]
  }
]
